{
  "dates": {
    "date1": {
      "title": "Unser erstes Date",
      "date": "",
      "time": "",
      "location": "📍 Noch kein Ort gesetzt",
      "description": "",
      "comments": [],
      "photos": []
    },
    "date2": {
      "title": "test date ",
      "date": "2025-08-19",
      "time": "12:00",
      "location": "Dieselstraße 7, Leverkusen",
      "description": "Test test ",
      "comments": [],
      "photos": [],
      "weather": {
        "condition": "Sonnig",
        "icon": "☀️",
        "temperature": 25,
        "humidity": 64,
        "season": "summer"
      }
    },
    "date3": {
      "title": "test test",
      "date": "2025-08-21",
      "time": "12:00",
      "location": "Strandläuferweg 34, 50829 Köln",
      "description": "hahassdh",
      "comments": [],
      "photos": [],
      "weather": {
        "condition": "Gewitter",
        "icon": "⛈️",
        "temperature": 20,
        "humidity": 56,
        "season": "summer"
      }
    }
  },
  "metadata": {
    "lastModified": 1755605028468,
    "lastModifiedBy": "device_h5e3w1odr_1755600001532",
    "lastUpdate": "2025-08-19T12:03:48.468Z",
    "version": "1.0",
    "totalDates": 3,
    "syncMethod": "github-api"
  }
}